[
  {
    "quote" : "I prefer the errors of enthusiasm to the indifference of wisdom.",
    "auther" : "Anatole France"
  },
  {
    "quote" : "A man can succeed at almost anything for which he has unlimited enthusiasm.",
    "auther" : "Charles M. Schwab"
  },
  {
    "quote" : "Catch on fire with enthusiasm and people will come for miles to watch you burn.",
    "auther" : "John Wesley"
  },
  {
    "quote" : "Charisma is the transference of enthusiasm.",
    "auther" : "Ralph Archbold"
  },
  {
    "quote" : "Common sense is compelled to make its way without the enthusiasm of anyone.",
    "auther" : "Edgar W. Howe"
  },
  {
    "quote" : "Courage is going from failure to failure without losing enthusiasm.",
    "auther" : "Winston Churchill"
  },
  {
    "quote" : "Creativity is a natural extension of our enthusiasm.",
    "auther" : "Earl Nightingale"
  },
  {
    "quote" : "Cushion the painful effects of hard blows by keeping the enthusiasm going strong, even if doing so requires struggle.",
    "auther" : "Norman Vincent Peale"
  },
  {
    "quote" : "Earnestness is enthusiasm tempered by reason.",
    "auther" : "Blaise Pascal"
  },
  {
    "quote" : "Enthusiasm is a vital element toward the individual success of every man or woman.",
    "auther" : "Conrad Hilton"
  },
  {
    "quote" : "Enthusiasm is everything. It must be taut and vibrating like a guitar string.",
    "auther" : "Pele"
  },
  {
    "quote" : "I prefer the errors of enthusiasm to the indifference of wisdom.",
    "auther" : "Anatole France"
  },
  {
    "quote" : "A man can succeed at almost anything for which he has unlimited enthusiasm.",
    "auther" : "Charles M. Schwab"
  },
  {
    "quote" : "Catch on fire with enthusiasm and people will come for miles to watch you burn.",
    "auther" : "John Wesley"
  },
  {
    "quote" : "Charisma is the transference of enthusiasm.",
    "auther" : "Ralph Archbold"
  },
  {
    "quote" : "Common sense is compelled to make its way without the enthusiasm of anyone.",
    "auther" : "Edgar W. Howe"
  },
  {
    "quote" : "Courage is going from failure to failure without losing enthusiasm.",
    "auther" : "Winston Churchill"
  },
  {
    "quote" : "Creativity is a natural extension of our enthusiasm.",
    "auther" : "Earl Nightingale"
  },
  {
    "quote" : "Cushion the painful effects of hard blows by keeping the enthusiasm going strong, even if doing so requires struggle.",
    "auther" : "Norman Vincent Peale"
  },
  {
    "quote" : "Earnestness is enthusiasm tempered by reason.",
    "auther" : "Blaise Pascal"
  },
  {
    "quote" : "Enthusiasm is a vital element toward the individual success of every man or woman.",
    "auther" : "Conrad Hilton"
  },
  {
    "quote" : "Enthusiasm is everything. It must be taut and vibrating like a guitar string.",
    "auther" : "Pele"
  },
  {
    "quote" : "Enthusiasm is the genius of sincerity and truth accomplishes no victories without it.",
    "auther" : "Edward Bulwer-Lytton"
  },
  {
    "quote" : "Enthusiasm is the inspiration of everything great. Without it no man is to be feared, and with it none despised.",
    "auther" : "Christian Nevell Bovee"
  },
  {
    "quote" : "Enthusiasm is the leaping lightning, not to be measured by the horse-power of the understanding.",
    "auther" : "Ralph Waldo Emerson"
  },
  {
    "quote" : "Enthusiasm is the mother of effort, and without it nothing great was ever achieved.",
    "auther" : "Ralph Waldo Emerson"
  },
  {
    "quote" : "Enthusiasm moves the world.",
    "auther" : "Arthur James Balfour"
  },
  {
    "quote" : "Enthusiasm releases the drive to carry you over obstacles and adds significance to all you do.",
    "auther" : "Norman Vincent Peale"
  },
  {
    "quote" : "Every production of genius must be the production of enthusiasm.",
    "auther" : "Benjamin Disraeli"
  },
  {
    "quote" : "Flaming enthusiasm, backed up by horse sense and persistence, is the quality that most frequently makes for success.",
    "auther" : "Dale Carnegie"
  },
  {
    "quote" : "If you aren't fired up with enthusiasm, you'll be fired with enthusiasm.",
    "auther" : "Vince Lombardi"
  },
  {
    "quote" : "If you can give your son or daughter only one gift, let it be enthusiasm.",
    "auther" : "Bruce Barton"
  },
  {
    "quote" : "In things pertaining to enthusiasm, no man is sane who does not know how to be insane on proper occasions.",
    "auther" : "Henry Ward Beecher"
  },
  {
    "quote" : "It is faith in something and enthusiasm for something that makes a life worth looking at.",
    "auther" : "Oliver Wendell Holmes"
  },
  {
    "quote" : "It's faith in something and enthusiasm for something that makes a life worth living.",
    "auther" : "Oliver Wendell Holmes"
  },
  {
    "quote" : "It's faith in something and enthusiasm for something that makes life worth living.",
    "auther" : "Oliver Wendell Holmes"
  },
  {
    "quote" : "Knowledge is power, but enthusiasm pulls the switch.",
    "auther" : "Ivern Ball"
  },
  {
    "quote" : "National enthusiasm is the nursery of genius.",
    "auther" : "Tuckerman"
  },
  {
    "quote" : "No battle of any importance can be won without enthusiasm.",
    "auther" : "John O'Brian"
  },
  {
    "quote" : "No person is ever good for much, that hasn't been swept off their feet by enthusiasm between ages twenty and thirty.",
    "auther" : "James A. Froude"
  },
  {
    "quote" : "None are so old as those who have outlived enthusiasm.",
    "auther" : "Henry David Thoreau"
  },
  {
    "quote" : "Nothing great was ever achieved without enthusiasm.",
    "auther" : "Ralph Waldo Emerson"
  },
  {
    "quote" : "Nothing great was ever achieved without enthusiasm.",
    "auther" : "Ralph Waldo Emerson"
  },
  {
    "quote" : "Nothing is so contagious as enthusiasm.",
    "auther" : "Samuel Taylor Coleridge"
  },
  {
    "quote" : "Nothing right can be accomplished in art without enthusiasm.",
    "auther" : "Robert Schumann"
  },
  {
    "quote" : "Protect your enthusiasm from the negativity of others.",
    "auther" : "H. Jackson Brown Jr"
  },
  {
    "quote" : "Ridicule has always been the enemy of enthusiasm, and the only worthy opponent to ridicule is success.",
    "auther" : "Oliver Goldsmith"
  },
  {
    "quote" : "Science is the great antidote to the poison of enthusiasm and superstition.",
    "auther" : "Adam Smith"
  },
  {
    "quote" : "Success consists of going from failure to failure without loss of enthusiasm.",
    "auther" : "Winston Churchill"
  },
  {
    "quote" : "Success is going from failure to failure without loss of enthusiasm.",
    "auther" : "Winston Churchill"
  },
  {
    "quote" : "The great accomplishments of man have resulted from the transmission of ideas and enthusiasm.",
    "auther" : "Thomas J. Watson"
  },
  {
    "quote" : "The real secret to success is enthusiasm.",
    "auther" : "Walter Chrysler"
  },
  {
    "quote" : "The secret of genius is to carry the spirit of the child into old age, which means never losing your enthusiasm.",
    "auther" : "Aldous Huxley"
  },
  {
    "quote" : "The sense of this word among the Greeks affords the noblest definition of it; enthusiasm signifies God in us.",
    "auther" : "Mme de Stael"
  },
  {
    "quote" : "There is a certain enthusiasm in liberty, that makes human nature rise above itself, in acts of bravery and heroism.",
    "auther" : "Alexander Hamilton"
  },
  {
    "quote" : "There is a real magic in enthusiasm. It spells the difference between mediocrity and accomplishment.",
    "auther" : "Norman Vincent Peale"
  },
  {
    "quote" : "To waken interest and kindle enthusiasm is the sure way to teach easily and successfully.",
    "auther" : "Tryon Edwards"
  },
  {
    "quote" : "Winners must learn to relish change with the same enthusiasm and energy that we have resisted it in the past.",
    "auther" : "Thomas J. Peters"
  },
  {
    "quote" : "You will do foolish things, but do them with enthusiasm.",
    "auther" : "Sidonie Gabrielle Colette"
  }
]
