[
  {
    "quote" : "A vow is a snare for sin.",
    "auther" : "Samuel Johnson"
  },
  {
    "quote" : "A sedentary life is the real sin against the Holy Spirit. Only those thoughts that come by walking have any value.",
    "auther" : "Friedrich Nietzsche"
  },
  {
    "quote" : "It is the public scandal that offends; to sin in secret is no sin at all.",
    "auther" : "Molière"
  },
  {
    "quote" : "The Bible will keep you from sin, or sin will keep you from the Bible.",
    "auther" : "Dwight L. Moody"
  },
  {
    "quote" : "A man does not sin by commission only, but often by ommission.",
    "auther" : "Marcus Aurelius"
  },
  {
    "quote" : "A private sin is not so prejudicial in this world, as a public indecency.",
    "auther" : "Miguel de Cervantes"
  },
  {
    "quote" : "After the first blush of sin comes its indifference.",
    "auther" : "Henry David Thoreau"
  },
  {
    "quote" : "And the Devil did grin, for his darling sin is pride that apes humility.",
    "auther" : "Samuel Taylor Coleridge"
  },
  {
    "quote" : "Anyone who considers arithmetical methods of producing random digits is, of course, in a state of sin.",
    "auther" : "John von Neumann"
  },
  {
    "quote" : "Be a sinner and sin strongly, but more strongly have faith and rejoice in Christ.",
    "auther" : "Martin Luther"
  },
  {
    "quote" : "Being seventy is not a sin.",
    "auther" : "Golda Meir"
  },
  {
    "quote" : "A vow is a snare for sin.",
    "auther" : "Samuel Johnson"
  },
  {
    "quote" : "A sedentary life is the real sin against the Holy Spirit. Only those thoughts that come by walking have any value.",
    "auther" : "Friedrich Nietzsche"
  },
  {
    "quote" : "It is the public scandal that offends; to sin in secret is no sin at all.",
    "auther" : "Molière"
  },
  {
    "quote" : "The Bible will keep you from sin, or sin will keep you from the Bible.",
    "auther" : "Dwight L. Moody"
  },
  {
    "quote" : "A man does not sin by commission only, but often by ommission.",
    "auther" : "Marcus Aurelius"
  },
  {
    "quote" : "A private sin is not so prejudicial in this world, as a public indecency.",
    "auther" : "Miguel de Cervantes"
  },
  {
    "quote" : "After the first blush of sin comes its indifference.",
    "auther" : "Henry David Thoreau"
  },
  {
    "quote" : "And the Devil did grin, for his darling sin is pride that apes humility.",
    "auther" : "Samuel Taylor Coleridge"
  },
  {
    "quote" : "Anyone who considers arithmetical methods of producing random digits is, of course, in a state of sin.",
    "auther" : "John von Neumann"
  },
  {
    "quote" : "Be a sinner and sin strongly, but more strongly have faith and rejoice in Christ.",
    "auther" : "Martin Luther"
  },
  {
    "quote" : "Being seventy is not a sin.",
    "auther" : "Golda Meir"
  },
  {
    "quote" : "Competition is a sin.",
    "auther" : "John D. Rockefeller"
  },
  {
    "quote" : "Convent. A place of retirement for women who wish for leisure to meditate upon the sin of idleness.",
    "auther" : "Ambrose Bierce"
  },
  {
    "quote" : "Cruelty is, perhaps, the worst kid of sin. Intellectual cruelty is certainly the worst kind of cruelty.",
    "auther" : "Gilbert Keith Chesterton"
  },
  {
    "quote" : "Every time that I think of the crucifixion of Christ, I commit the sin of envy.",
    "auther" : "Simone Weil"
  },
  {
    "quote" : "Everything that used to be a sin, is now a disease.",
    "auther" : "Bill Maher"
  },
  {
    "quote" : "Failing to be there when a man wants her is a woman's greatest sin, except to be there when he doesn't want her.",
    "auther" : "Helen Rowland"
  },
  {
    "quote" : "For any sin, we all suffer. That is why our suffering is endless.",
    "auther" : "Berry Wendell"
  },
  {
    "quote" : "For right is right, since God is God and right the day must win. To doubt would be disloyalty, to falter would be sin.",
    "auther" : "Frederick W. Faber"
  },
  {
    "quote" : "For the sin they do by two and two they must pay for one by one.",
    "auther" : "Joseph Rudyard Kipling"
  },
  {
    "quote" : "From Obedience and submission comes all our virtues, and all sin is comes from self-opinion.",
    "auther" : "Michel Eyquem De Montaigne"
  },
  {
    "quote" : "God had one son on earth without sin, but never one without suffering.",
    "auther" : "St. Augustine of Hippo"
  },
  {
    "quote" : "Going to the opera, like getting drunk, is a sin that carries its own punishment with it.",
    "auther" : "Hannah More"
  },
  {
    "quote" : "Great abundance of riches cannot be gathered and kept by any man without sin.",
    "auther" : "Desiderius Erasmus"
  },
  {
    "quote" : "Great eagerness in the pursuit of wealth, pleasure, or honor, cannot exist without sin.",
    "auther" : "Desiderius Erasmus"
  },
  {
    "quote" : "He that falls into sin is a man; that grieves at it, is a saint; that boasteth of it, is a devil.",
    "auther" : "Thomas Fuller"
  },
  {
    "quote" : "He that would be angry and sin not, must not be angry with anything but sin.",
    "auther" : "Thomas Secker"
  },
  {
    "quote" : "He who is completely sanctified, or cleansed from all sin, and dies in this state, is fit for glory.",
    "auther" : "Adam Clarke"
  },
  {
    "quote" : "He who is upright in his way of life and free from sin.",
    "auther" : "Horace"
  },
  {
    "quote" : "How shall I lose the sin, yet keep the sense, and love the offender, yet detest the offence?",
    "auther" : "Alexander Pope"
  },
  {
    "quote" : "I believe in the forgiveness of sin and the redemption of ignorance.",
    "auther" : "Adlai E. Stevenson II"
  },
  {
    "quote" : "I count religion but a childish toy, and hold there is no sin but innocence.",
    "auther" : "Christopher Marlowe"
  },
  {
    "quote" : "If it be a sin to covet honor I am the most offending soul alive.",
    "auther" : "William Shakespeare"
  },
  {
    "quote" : "If it were possible to have a life absolutely free from every feeling of sin, what a terrifying vacuum it would be!",
    "auther" : "Cesare Pavese"
  },
  {
    "quote" : "If the misery of the poor be caused not by the laws of nature, but by our institutions, great is our sin.",
    "auther" : "Charles Darwin"
  },
  {
    "quote" : "If there is such a thing as sin in this world, I think it must be shutting oneself up against hope.",
    "auther" : "Gail Godwin"
  },
  {
    "quote" : "If you're going to sin, sin against God, not the bureaucracy; God will forgive you but the bureaucracy won t.",
    "auther" : "Hyman G. Rickover"
  },
  {
    "quote" : "Ignorance is not innocence but sin.",
    "auther" : "Robert Browning"
  },
  {
    "quote" : "Ignorance is not innocence, but sin.",
    "auther" : "Robert Browning"
  },
  {
    "quote" : "In my family, the biggest sin was to buy retail.",
    "auther" : "Woody Allen"
  },
  {
    "quote" : "It ain't sin if you crack a few laws now and then, just so long as you don't break any.",
    "auther" : "Mae West"
  },
  {
    "quote" : "It is a sin to be poor.",
    "auther" : "Charles J. Fillmore"
  },
  {
    "quote" : "It is a sin to believe evil of others, but it is rarely a mistake.",
    "auther" : "Henry Louis Mencken"
  },
  {
    "quote" : "It is a sin to believe evil of others, but it is seldom a mistake.",
    "auther" : "Henry Louis Mencken"
  },
  {
    "quote" : "It is the grace of God, that shows and condemns the sin that humbles us.",
    "auther" : "Adam Clarke"
  },
  {
    "quote" : "It makes a great deal of difference whether one wills not to sin or has not the knowledge to sin.",
    "auther" : "Seneca"
  },
  {
    "quote" : "Laughter does not seem to be a sin, but it leads to sin.",
    "auther" : "St. John Chrysosatom"
  },
  {
    "quote" : "Lukewarmness I account a sin, as great in love as in religion.",
    "auther" : "Abraham Cowley"
  },
  {
    "quote" : "Many without punishment, none without sin.",
    "auther" : "John Ray"
  },
  {
    "quote" : "Most dangerous is that temptation that doth good us on to sin to loving virtue.",
    "auther" : "William Shakespeare"
  },
  {
    "quote" : "Nothing emboldens sin so much as mercy.",
    "auther" : "William Shakespeare"
  },
  {
    "quote" : "One leak will sink a ship: and one sin will destroy a sinner.",
    "auther" : "John Bunyan"
  },
  {
    "quote" : "Original thought is like original sin: both happened before you were born to people you could not have possibly met.",
    "auther" : "Fran Lebowitz"
  },
  {
    "quote" : "Preachers denounce sin as if it was available to everyone.",
    "auther" : "Frank Dane"
  },
  {
    "quote" : "Pride is the master sin of the devil, and the devil is the father of lies.",
    "auther" : "Edwin Hubbel Chapin"
  },
  {
    "quote" : "Really to sin you have to be serious about it.",
    "auther" : "Henrik Ibsen"
  },
  {
    "quote" : "Redemption from sin is greater then redemption from affliction.",
    "auther" : "Daniel Defoe"
  },
  {
    "quote" : "Religion has done love a great service by making it a sin.",
    "auther" : "Anatole France"
  },
  {
    "quote" : "Remorse is impotence, it will sin again. Only repentance is strong, it can end everything.",
    "auther" : "Henry Miller"
  },
  {
    "quote" : "Remorse is the pain of sin.",
    "auther" : "Theodore Parker"
  },
  {
    "quote" : "Repentance is but want of power of sin.",
    "auther" : "John Dryden"
  },
  {
    "quote" : "Repentance is but want of power to sin.",
    "auther" : "John Dryden"
  },
  {
    "quote" : "Repentance may be old-fashioned, but it is not outdated so long as there is sin.",
    "auther" : "J. C. Macaulay"
  },
  {
    "quote" : "Self-love, is not so vile a sin as self-neglecting.",
    "auther" : "William Shakespeare"
  },
  {
    "quote" : "She feared no danger, for she knew no sin.",
    "auther" : "John Dryden"
  },
  {
    "quote" : "Sin brought death, and death will disappear with the disappearance of sin.",
    "auther" : "Mary Baker Eddy"
  },
  {
    "quote" : "Sin has many tools, but a lie is the handle that fits them all.",
    "auther" : "Oliver Wendell Holmes"
  },
  {
    "quote" : "Sin has many tools, but a lie is the handle which fits them all.",
    "auther" : "Oliver Wendell Holmes"
  },
  {
    "quote" : "Sin in this country has been always said to be rather calculating than impulsive.",
    "auther" : "Frank Moore Colby"
  },
  {
    "quote" : "Sin is geographical.",
    "auther" : "Bertrand Russell"
  },
  {
    "quote" : "Sin is too stupid to see beyond itself.",
    "auther" : "Alfred Lord Tennyson"
  },
  {
    "quote" : "Sin is whatever obscures the soul.",
    "auther" : "André Gide"
  },
  {
    "quote" : "Sin, guilt, neurosis -they are one and the same, the fruit of the tree of knowledge.",
    "auther" : "Henry Miller"
  },
  {
    "quote" : "SIN: Self-Inflicted Nonsense",
    "auther" : "Eric Butterworth"
  },
  {
    "quote" : "Some rise by sin, and some by virtue fall.",
    "auther" : "William Shakespeare"
  },
  {
    "quote" : "Starvation, and not sin, is the parent of modern crime.",
    "auther" : "Oscar Wilde"
  },
  {
    "quote" : "Success is the one unpardonable sin against one's fellows.",
    "auther" : "Ambrose Bierce"
  },
  {
    "quote" : "That which we call sin in others, is experiment for us.",
    "auther" : "Ralph Waldo Emerson"
  },
  {
    "quote" : "The deepest sin against the human mind is to believe things without evidence.",
    "auther" : "Aldous Huxley"
  },
  {
    "quote" : "The essence of all immorality and sin is making ourselves the center around which we subordinate all interest.",
    "auther" : "Cecil J. Sharpe"
  },
  {
    "quote" : "The first and greatest punishment of the sinner is the conscience of sin.",
    "auther" : "Seneca"
  },
  {
    "quote" : "The first and worst of all frauds is to cheat one's self. All sin is easy after that.",
    "auther" : "Pearl Bailey"
  },
  {
    "quote" : "The first sin in our universe was Lucifer's self conceit.",
    "auther" : "Thomas Carlyle"
  },
  {
    "quote" : "The first step in a person's salvation is knowledge of their sin.",
    "auther" : "Seneca"
  },
  {
    "quote" : "The German people is not marked by original sin, but by original nobility.",
    "auther" : "Alfred Rosenberg"
  },
  {
    "quote" : "The only deadly sin I know is cynicism.",
    "auther" : "Henry Lewis Stimson"
  },
  {
    "quote" : "The only people who should really sin are the people who can sin and grin.",
    "auther" : "Ogden Nash"
  },
  {
    "quote" : "The only sin passion can commit is to be joyless.",
    "auther" : "Dorothy L. Sayers"
  },
  {
    "quote" : "The only sin that we never forgive in each other is a difference in opinion.",
    "auther" : "Ralph Waldo Emerson"
  },
  {
    "quote" : "The ultimate sin of any performer is contempt for the audience.",
    "auther" : "Lester Bangs"
  },
  {
    "quote" : "The wages of sin are death, but by the time taxes are taken out, it's just sort of a tired feeling.",
    "auther" : "Paula Poundstone"
  },
  {
    "quote" : "The worst sin... is... to be indifferent.",
    "auther" : "George Bernard Shaw"
  },
  {
    "quote" : "Then is it sin to rush into the secret house of death. Ere death dare come to us?",
    "auther" : "William Shakespeare"
  },
  {
    "quote" : "There is no sin except stupidity.",
    "auther" : "Oscar Wilde"
  },
  {
    "quote" : "There is only one sin and that is theft.",
    "auther" : "Khaled Hosseini"
  },
  {
    "quote" : "To abstain from sin when one can no longer sin is to be forsaken by sin, not to forsake it.",
    "auther" : "St. Augustine of Hippo"
  },
  {
    "quote" : "To put away one's own original thoughts in order to take up a book is a sin against the Holy Ghost.",
    "auther" : "Barbara Tuchman"
  },
  {
    "quote" : "To say of shame - what is it? Of virtue - we can miss it; Of sin-we can kiss it, And it's no longer sin.",
    "auther" : "A. C. Swinburne"
  },
  {
    "quote" : "To sin by silence when they should protest makes cowards of men.",
    "auther" : "Abraham Lincoln"
  },
  {
    "quote" : "To those whose God is honor; only disgrace is a sin.",
    "auther" : "David Hare"
  },
  {
    "quote" : "We condemn a sin before we have even tried it.",
    "auther" : "Henry S. Haskins"
  },
  {
    "quote" : "When it comes to finances, remember that there are no withholding taxes on the wages of sin.",
    "auther" : "Mae West"
  },
  {
    "quote" : "Who are you to condemn another's sin? He who condemns sin becomes part of it, espouses it.",
    "auther" : "Georges Bernanos"
  },
  {
    "quote" : "Why did I write? What sin to me unknown dipped me in ink, my parents , or my own?",
    "auther" : "Alexander Pope"
  },
  {
    "quote" : "Work with some men is as besetting a sin as idleness.",
    "auther" : "Samuel Butler"
  },
  {
    "quote" : "Writing saved me from the sin and inconvenience of violence.",
    "auther" : "Alice Walker"
  },
  {
    "quote" : "Writing saved me from the sin and inconvenience of violence.",
    "auther" : "Alice Walker"
  }
]
